{
  "db_name": "PostgreSQL",
  "query": "SELECT address, balance FROM participants WHERE address = $1 AND is_active = true",
  "describe": {
    "columns": [
      {
        "ordinal": 0,
        "name": "address",
        "type_info": "Text"
      },
      {
        "ordinal": 1,
        "name": "balance",
        "type_info": "Int8"
      }
    ],
    "parameters": {
      "Left": [
        "Text"
      ]
    },
    "nullable": [
      false,
      true
    ]
  },
  "hash": "9825046feaf567eea9d5a2067bbbca142484e06261c49eb2417b724c5d4fc927"
}
